altcli_helper/__init__.py
altcli_helper/client.py
altcli_helper/main.py
altcli_helper-0.1.0.dist-info/entry_points.txt
altcli_helper-0.1.0.dist-info/LICENSE.md
altcli_helper-0.1.0.dist-info/METADATA
altcli_helper-0.1.0.dist-info/WHEEL
altcli_helper-0.1.0.dist-info/RECORD
