Metadata-Version: 2.1
Name: altcli_helper
Version: 0.1.0
Summary: 
Author: D0rkKnight
Author-email: shouhanzen@gmail.com
Requires-Python: >=3.11,<4.0
Classifier: Programming Language :: Python :: 3
Classifier: Programming Language :: Python :: 3.11
Requires-Dist: fastapi[all] (>=0.104.0,<0.105.0)
Requires-Dist: openai (>=0.28.1,<0.29.0)
